blip/__init__.py
blip/blip.py
blip-0.1.0.dist-info/LICENSE
blip-0.1.0.dist-info/METADATA
blip-0.1.0.dist-info/WHEEL
blip-0.1.0.dist-info/entry_points.txt
blip-0.1.0.dist-info/top_level.txt
blip-0.1.0.dist-info/RECORD
