Metadata-Version: 2.1
Name: blip
Version: 0.1.0
Summary: Turn a target string into a list of bit flipped strings
Home-page: https://github.com/zmallen/blip
Author: techy
Author-email: zma4580@gmail.com
License: MIT
Platform: UNKNOWN
Classifier: Programming Language :: Python :: 3
